marzban/__init__.py
marzban/admin.py
marzban/core.py
marzban/node.py
marzban/panel.py
marzban/subscription.py
marzban/system.py
marzban/user.py
marzban/user_template.py
marzban/utils.py
marzban/models/hosts_model.py
marzban/models/user_model.py
marzban/models/user_template_model.py
marzban_client-0.1.1.dist-info/METADATA
marzban_client-0.1.1.dist-info/WHEEL
marzban_client-0.1.1.dist-info/top_level.txt
marzban_client-0.1.1.dist-info/RECORD
